{"is_source_file": true, "format": "JavaScript (React JSX)", "description": "This file serves as the entry point for the React frontend application. It imports React modules and components, sets up the root DOM node, and renders the main App component.", "external_files": ["react", "react-dom/client", "./index.css", "./App"], "external_methods": ["ReactDOM.createRoot", "root.render"], "published": [], "classes": [], "methods": [{"name": "ReactDOM.createRoot", "description": "Creates a root to manage rendering of React components into the DOM."}, {"name": "root.render", "description": "Renders the specified React component into the DOM."}], "calls": ["ReactDOM.createRoot", "root.render"], "search-terms": ["index.js", "ReactDOM", "App component", "entry point", "render"], "state": 2, "file_id": 5, "knowledge_revision": 28, "git_revision": "2fdfb8246726ca32f3a388e58048f15f33b68cbd", "revision_history": [{"24": "2fdfb8246726ca32f3a388e58048f15f33b68cbd"}, {"28": "2fdfb8246726ca32f3a388e58048f15f33b68cbd"}], "ctags": [{"_type": "tag", "name": "root", "path": "/home/kavia/workspace/code-generation/serverless-e-commerce-checkout-system-215564-215574/ecommerce_frontend/src/index.js", "pattern": "/^const root = ReactDOM.createRoot(document.getElementById('root'));$/", "language": "JavaScript", "kind": "constant"}], "hash": "355853b40cbc04be74f0c83ea13b29e2", "format-version": 4, "code-base-name": "ecommerce_frontend", "filename": "ecommerce_frontend/src/index.js"}